spatial_spec/__init__.py
spatial_spec/automaton_planning.py
spatial_spec/geometry.py
spatial_spec/logic.py
spatial_spec/ltlf2dfa_nx.py
spatial_spec/spatial.lark
spatial_spec-0.1.1.dist-info/LICENSE
spatial_spec-0.1.1.dist-info/METADATA
spatial_spec-0.1.1.dist-info/WHEEL
spatial_spec-0.1.1.dist-info/RECORD
