Metadata-Version: 2.1
Name: spatial-spec
Version: 0.1.1
Summary: 
License: LICENSE
Author: Georg Schuppe
Author-email: georg.schuppe@gmail.com
Requires-Python: >=3.8,<4.0
Classifier: License :: Other/Proprietary License
Classifier: Programming Language :: Python :: 3
Classifier: Programming Language :: Python :: 3.8
Classifier: Programming Language :: Python :: 3.9
Classifier: Programming Language :: Python :: 3.10
Classifier: Programming Language :: Python :: 3.11
Requires-Dist: lark (>=1.1.5,<2.0.0)
Requires-Dist: ltlf2dfa (>=1.0.2,<2.0.0)
Requires-Dist: matplotlib (>=3.7.1,<4.0.0)
Requires-Dist: networkx (>=3.1,<4.0)
Requires-Dist: numpy (>=1.24.3,<2.0.0)
Requires-Dist: shapely (>=2.0.1,<3.0.0)
